LICENSE
MANIFEST.in
README.md
setup.cfg
setup.py
ctp/version.txt
ctp/header/DataCollect.h
ctp/header/ThostFtdcMdApi.h
ctp/header/ThostFtdcTraderApi.h
ctp/header/ThostFtdcUserApiDataType.h
ctp/header/ThostFtdcUserApiStruct.h
ctp/header/error.dtd
ctp/header/error.xml
ctp/linux/libLinuxDataCollect.so
ctp/linux/libthostmduserapi_se.so
ctp/linux/libthosttraderapi_se.so
ctp/win/WinDataCollect.dll
ctp/win/WinDataCollect.lib
ctp/win/thostmduserapi_se.dll
ctp/win/thostmduserapi_se.lib
ctp/win/thosttraderapi_se.dll
ctp/win/thosttraderapi_se.lib
ctpwrapper/ApiStructure.py
ctpwrapper/Md.py
ctpwrapper/MdApi.pyx
ctpwrapper/Trader.py
ctpwrapper/TraderApi.pyx
ctpwrapper/__init__.py
ctpwrapper/base.py
ctpwrapper/datacollect.pyx
ctpwrapper.egg-info/PKG-INFO
ctpwrapper.egg-info/SOURCES.txt
ctpwrapper.egg-info/dependency_links.txt
ctpwrapper.egg-info/top_level.txt
ctpwrapper/cppheader/CMdAPI.h
ctpwrapper/cppheader/CTraderAPI.h
ctpwrapper/headers/DataCollect.pxd
ctpwrapper/headers/ThostFtdcUserApiDataType.pxd
ctpwrapper/headers/ThostFtdcUserApiStruct.pxd
ctpwrapper/headers/__init__.pxd
ctpwrapper/headers/cMdAPI.pxd
ctpwrapper/headers/cTraderApi.pxd